sbom4php/__init__.py
sbom4php/cli.py
sbom4php/scanner.py
sbom4php/version.py
sbom4php-0.1.0.dist-info/LICENSE
sbom4php-0.1.0.dist-info/METADATA
sbom4php-0.1.0.dist-info/WHEEL
sbom4php-0.1.0.dist-info/entry_points.txt
sbom4php-0.1.0.dist-info/top_level.txt
sbom4php-0.1.0.dist-info/RECORD
